blockit/__init__.py
blockit/__main__.py
blockit/cli.py
blockit/crypto_algorithms.py
blockit/reverse_encryption_api.py
blockit-0.0.5.dist-info/entry_points.txt
blockit-0.0.5.dist-info/LICENSE
blockit-0.0.5.dist-info/WHEEL
blockit-0.0.5.dist-info/METADATA
blockit-0.0.5.dist-info/RECORD
