Metadata-Version: 2.1
Name: blockit
Version: 0.0.5
Summary: blockit - cli tool for encrypting and decrypting strings
Author-email: 0xsirsaif <sirsaif99@gmail.com>
Requires-Python: >=3.9
Classifier: License :: OSI Approved :: MIT License
Classifier: Development Status :: 4 - Beta
Classifier: Intended Audience :: Developers
Classifier: Programming Language :: Python :: 3.7
Classifier: Programming Language :: Python :: 3.8
Classifier: Programming Language :: Python :: 3.9
Classifier: Programming Language :: Python :: 3.10
Classifier: Programming Language :: Python :: 3 :: Only
Classifier: Topic :: Security :: Cryptography
Requires-Dist: typer >= 0.9.0
Requires-Dist: httpx >= 0.24.1
Requires-Dist: pytest ; extra == "dev"
Requires-Dist: isort ; extra == "dev"
Requires-Dist: black ; extra == "dev"
Requires-Dist: mypy ; extra == "dev"
Requires-Dist: codecov ; extra == "dev"
Requires-Dist: pytest-cov ; extra == "dev"
Requires-Dist: flit ; extra == "dev"
Requires-Dist: bumpversion ; extra == "dev"
Project-URL: Documentation, https://github/0xsirsaif/blockit
Provides-Extra: dev
